{"Ljubljana": "Yes", "Paris": "Yes", "Namur": "Yes", "Rennes": "Yes", "Kyoto-Minaport": "Yes", "Lyon": "Yes", "Washington-DC": "Yes", "Cergy-Pontoise": "Yes", "New-York": "Yes", "Creteil": "Yes", "Bruxelles-Capitale": "Yes", "Rouen": "Yes", "Vilnius": "Yes", "Lillestrom": "Yes", "Goteborg": "Yes", "Seville": "Yes", "Marseille": "Yes", "Stockholm": "Yes", "Lund": "Yes", "Valence": "Yes", "Toulouse": "Yes", "Mulhouse": "Yes", "London": "No", "Luxembourg": "Yes", "Kazan": "Yes", "Chattanooga": "No", "Nancy": "Yes", "Amiens": "Yes", "Toyama": "Yes", "Chicago": "No", "Minneapolis": "Yes", "Besancon": "Yes", "Bay-Area": "No", "Dublin": "Yes"}